messy_string/RSError.py
messy_string/RSParam.py
messy_string/__init__.py
messy_string/__main__.py
messy_string/messy_string.py
messy_string-0.3.0.dist-info/METADATA
messy_string-0.3.0.dist-info/WHEEL
messy_string-0.3.0.dist-info/entry_points.txt
messy_string-0.3.0.dist-info/top_level.txt
messy_string-0.3.0.dist-info/RECORD
