Metadata-Version: 2.1
Name: messy-string
Version: 0.3.0
Summary: A tool to generate random character strings based on parameters
Home-page: https://github.com/motya1121/messy_string
Author: motya0414
Author-email: motya0414@hotmail.co.jp
License: MIT
Keywords: random string
Platform: UNKNOWN
Classifier: License :: OSI Approved :: MIT License
Classifier: Programming Language :: Python :: 3.6
